{"service": "ec2", "region": "us-east-1", "profile": null, "operation": "DescribeKeyPairs", "response": {"KeyPairs": [{"KeyPairId": "key-05122b42f4f6433f9", "KeyFingerprint": "82:7c:15:1e:a0:a7:62:e8:f5:94:e7:8c:fb:e8:73:56:a1:a3:50:97", "KeyName": "AWS My Web Server EC2 Instance1", "KeyType": "rsa", "Tags": [], "CreateTime": "2022-05-13T03:42:24+00:00"}], "ResponseMetadata": {"RequestId": "b883108f-640b-46bc-8682-c1f5a71b4ba9", "HTTPStatusCode": 200, "HTTPHeaders": {"x-amzn-requestid": "b883108f-640b-46bc-8682-c1f5a71b4ba9", "cache-control": "no-cache, no-store", "strict-transport-security": "max-age=31536000; includeSubDomains", "content-type": "text/xml;charset=UTF-8", "content-length": "609", "date": "Mon, 13 Jun 2022 07:39:27 GMT", "server": "AmazonEC2"}, "RetryAttempts": 0}}}